pocket_agent/__init__.py
pocket_agent/agent.py
pocket_agent/client.py
pocket_agent/docs/00_index.md
pocket_agent/docs/01_getting-started.md
pocket_agent/docs/02_core-concepts.md
pocket_agent/docs/03_hooks-and-events.md
pocket_agent/docs/04_multi-model-support.md
pocket_agent/docs/05_client.md
pocket_agent/docs/06_multi-agent.md
pocket_agent/docs/07_agent-as-a-server.md
pocket_agent/docs/08_testing.md
pocket_agent/docs/__init__.py
pocket_agent/pocket_dump/__init__.py
pocket_agent/pocket_dump/cli.py
pocket_agent/utils/console_formatter.py
pocket_agent/utils/logger.py
pocket_agent-0.2.23.dist-info/METADATA
pocket_agent-0.2.23.dist-info/WHEEL
pocket_agent-0.2.23.dist-info/entry_points.txt
pocket_agent-0.2.23.dist-info/licenses/LICENSE
pocket_agent-0.2.23.dist-info/RECORD
