Metadata-Version: 2.4
Name: pocket-agent
Version: 0.2.23
Summary: A lightweight, extensible framework for building LLM agents with Model Context Protocol (MCP) support
Project-URL: Homepage, https://github.com/DIR-LAB/pocket-agent
Project-URL: Repository, https://github.com/DIR-LAB/pocket-agent
Project-URL: Bug Tracker, https://github.com/DIR-LAB/pocket-agent/issues
Project-URL: Documentation, https://github.com/DIR-LAB/pocket-agent#readme
Project-URL: Changelog, https://github.com/DIR-LAB/pocket-agent/releases
Author-email: Chris Egersdoerfer <cegersdoerfer@gmail.com>
Maintainer-email: Chris Egersdoerfer <cegersdoerfer@gmail.com>
License-Expression: MIT
License-File: LICENSE
Keywords: agent,ai,llm,mcp,model-context-protocol
Classifier: Development Status :: 4 - Beta
Classifier: Intended Audience :: Developers
Classifier: License :: OSI Approved :: MIT License
Classifier: Operating System :: OS Independent
Classifier: Programming Language :: Python :: 3
Classifier: Programming Language :: Python :: 3.12
Classifier: Programming Language :: Python :: 3.13
Classifier: Topic :: Scientific/Engineering :: Artificial Intelligence
Classifier: Topic :: Software Development :: Libraries :: Python Modules
Requires-Python: >=3.12
Requires-Dist: fastmcp>=2.12.2
Requires-Dist: litellm>=1.76.3
